datalib/__init__.py
datalib/analysis/__init__.py
datalib/analysis/clustering.py
datalib/analysis/regression.py
datalib/preprocessing/__init__.py
datalib/preprocessing/csv_handler.py
datalib/preprocessing/transformations.py
datalib/statslib/__init__.py
datalib/statslib/basic_stats.py
datalib/statslib/statistical_tests.py
datalib/visualization/__init__.py
datalib/visualization/advanced_viz.py
datalib/visualization/charts.py
tests/__init__.py
tests/conftest.py
tests/test_basic_stats.py
tests/test_charts.py
tests/test_csv_handler.py
tests/test_models.py
tests/test_transformations.py
datalib_genta-0.1.2.dist-info/LICENSE
datalib_genta-0.1.2.dist-info/METADATA
datalib_genta-0.1.2.dist-info/WHEEL
datalib_genta-0.1.2.dist-info/top_level.txt
datalib_genta-0.1.2.dist-info/RECORD
