Metadata-Version: 2.1
Name: datalib_genta
Version: 0.1.2
Summary: A Python library for data manipulation, statistical analysis, and machine learning.
Author: Ibrahim Trabelsi
Author-email: Trabelsi_Ibrahim@hotmail.com
License: MIT
Classifier: Programming Language :: Python :: 3
Classifier: License :: OSI Approved :: MIT License
Classifier: Operating System :: OS Independent
Requires-Python: >=3.7
License-File: LICENSE
